bson_tools/__init__.py
bson_tools/cli.py
bson_tools-0.1.0.dist-info/LICENSE
bson_tools-0.1.0.dist-info/METADATA
bson_tools-0.1.0.dist-info/WHEEL
bson_tools-0.1.0.dist-info/entry_points.txt
bson_tools-0.1.0.dist-info/top_level.txt
bson_tools-0.1.0.dist-info/RECORD
