Metadata-Version: 2.1
Name: bson-tools
Version: 0.1.0
Summary: A comprehensive toolkit for BSON file manipulation
Home-page: https://github.com/janketj/bson-tools
Author: Jannik Janket
Author-email: jannikjanket@gmail.com
Classifier: Development Status :: 4 - Beta
Classifier: Intended Audience :: Developers
Classifier: License :: OSI Approved :: MIT License
Classifier: Programming Language :: Python :: 3
Classifier: Programming Language :: Python :: 3.6
Classifier: Programming Language :: Python :: 3.7
Classifier: Programming Language :: Python :: 3.8
Classifier: Programming Language :: Python :: 3.9
License-File: LICENSE
Requires-Dist: pymongo>=3.11.0
Requires-Dist: PyYAML>=5.4.1
